ezomero/__init__.py
ezomero/_ezomero.py
ezomero/_gets.py
ezomero/_importer.py
ezomero/_misc.py
ezomero/_posts.py
ezomero/json_api.py
ezomero/rois.py
ezomero-3.2.2.dist-info/licenses/LICENSE
ezomero-3.2.2.dist-info/METADATA
ezomero-3.2.2.dist-info/WHEEL
ezomero-3.2.2.dist-info/top_level.txt
ezomero-3.2.2.dist-info/RECORD
