Metadata-Version: 2.4
Name: ezomero
Version: 3.2.2
Summary: A suite of convenience functions for working with OMERO.
Maintainer-email: Erick Ratamero <erick.ratamero@embl.de>, Dave Mellert <dave.mellert@jax.org>
License-Expression: GPL-2.0
Project-URL: Repository, https://github.com/erickmartins/ezomero
Requires-Python: >=3.9
License-File: LICENSE
Requires-Dist: omero-py<=5.22.0,>=5.13.0
Requires-Dist: numpy<2.0,>=1.22
Provides-Extra: tables
Requires-Dist: pandas; extra == "tables"
Provides-Extra: docs
Requires-Dist: sphinx; extra == "docs"
Dynamic: license-file
